easy_timezones/__init__.py
easy_timezones/middleware.py
easy_timezones/signals.py
easy_timezones/tests.py
easy_timezones/urls.py
easy_timezones/utils.py
easy_timezones/views.py
django_easy_timezones_redux-1.0.4.dist-info/LICENSE
django_easy_timezones_redux-1.0.4.dist-info/METADATA
django_easy_timezones_redux-1.0.4.dist-info/WHEEL
django_easy_timezones_redux-1.0.4.dist-info/top_level.txt
django_easy_timezones_redux-1.0.4.dist-info/RECORD
