Metadata-Version: 2.1
Name: django-easy-timezones-redux
Version: 1.0.4
Summary: Easy timezones for Django (>=1.11) based on MaxMind GeoIP2.
Home-page: https://github.com/maurizi/django-easy-timezones
Author: Rich Jones
Maintainer: Michael Maurizi
Maintainer-email: michael@maurizi.org
License: Apache License
Platform: UNKNOWN
Classifier: Environment :: Web Environment
Classifier: Framework :: Django
Classifier: Intended Audience :: Developers
Classifier: License :: OSI Approved :: Apache Software License
Classifier: Operating System :: OS Independent
Classifier: Programming Language :: Python
Classifier: Programming Language :: Python :: 2.7
Classifier: Programming Language :: Python :: 3.5
Classifier: Programming Language :: Python :: 3.6
Classifier: Topic :: Internet :: WWW/HTTP
Classifier: Topic :: Internet :: WWW/HTTP :: Dynamic Content
Requires-Dist: Django (>=1.8)
Requires-Dist: geoip2 (>=2.9.0)
Requires-Dist: ipaddress (>=1.0.16)
Requires-Dist: pytz
Requires-Dist: wheel (>=0.29.0)
